aw/__init__.py
aw/base.py
aw/cosmo.py
aw/loading.py
aw/orchestration.py
aw/preparing.py
aw/routing.py
aw/tools.py
aw/util.py
aw/validation.py
aw-0.1.2.dist-info/licenses/LICENSE
tests/__init__.py
tests/conftest.py
tests/test_loading.py
tests/test_validation.py
tests/test_workflow.py
aw-0.1.2.dist-info/METADATA
aw-0.1.2.dist-info/WHEEL
aw-0.1.2.dist-info/top_level.txt
aw-0.1.2.dist-info/RECORD
