Metadata-Version: 2.4
Name: aw
Version: 0.1.2
Summary: AI Agentic Workflows for data preparation and transformation
Home-page: https://github.com/thorwhalen/aw
Author: Thor Whalen
License: mit
Keywords: ai,agents,agentic-workflows,data-preparation,llm,react-pattern,pandas,dataframe,cosmograph,visualization,code-execution,validation,orchestration,claude-desktop,mcp
Platform: any
Requires-Python: >=3.10
License-File: LICENSE
Requires-Dist: pandas
Requires-Dist: config2py
Requires-Dist: pydantic
Requires-Dist: oa
Provides-Extra: llm
Requires-Dist: openai; extra == "llm"
Requires-Dist: oa; extra == "llm"
Provides-Extra: cosmograph
Requires-Dist: cosmograph; extra == "cosmograph"
Provides-Extra: langchain
Requires-Dist: langchain; extra == "langchain"
Requires-Dist: langchain-experimental; extra == "langchain"
Provides-Extra: all
Requires-Dist: openai; extra == "all"
Requires-Dist: oa; extra == "all"
Requires-Dist: cosmograph; extra == "all"
Requires-Dist: langchain; extra == "all"
Requires-Dist: langchain-experimental; extra == "all"
Provides-Extra: testing
Requires-Dist: pytest; extra == "testing"
Requires-Dist: pytest-cov; extra == "testing"
Requires-Dist: openai; extra == "testing"
Requires-Dist: oa; extra == "testing"
Dynamic: license-file
